search_llm_actions/__init__.py
search_llm_actions/deploy_vllm.py
search_llm_actions/llm_caller.py
search_llm_actions/main.py
search_llm_actions/search.py
search_llm_actions-0.0.1.dist-info/METADATA
search_llm_actions-0.0.1.dist-info/WHEEL
search_llm_actions-0.0.1.dist-info/top_level.txt
search_llm_actions-0.0.1.dist-info/RECORD
