Metadata-Version: 2.1
Name: search-llm-actions
Version: 0.0.1
Summary: ('search_llm_actions provides a simple template to collect action trajectories from local (e.g. vllm servers) or remote (e.g. togetherai api) llms by search.',)
Home-page: https://github.com/bebetterest/search_llm_actions
Author: Betterest
Author-email: bebetterest@outlook.com
License: MIT
Classifier: License :: OSI Approved :: MIT License
Classifier: Programming Language :: Python
Classifier: Programming Language :: Python :: 3
Classifier: Programming Language :: Python :: 3.6
Classifier: Programming Language :: Python :: Implementation :: CPython
Classifier: Programming Language :: Python :: Implementation :: PyPy
Requires-Python: >=3.6.0
Requires-Dist: vllm
Requires-Dist: tqdm
Requires-Dist: together
Requires-Dist: jsonlines
Requires-Dist: transformers
